MANIFEST.in
setup.py
django_genius.egg-info/PKG-INFO
django_genius.egg-info/SOURCES.txt
django_genius.egg-info/dependency_links.txt
django_genius.egg-info/entry_points.txt
django_genius.egg-info/requires.txt
django_genius.egg-info/top_level.txt
starts/__init__.py
starts/addCodeSettings.py
starts/addHost.py
starts/addInstallApp.py
starts/addMail.py
starts/addMiddleware.py
starts/addSecret.py
starts/fileCheck.py
starts/multiUser.py
starts/react.py
starts/scheduler.py
starts/starts.py
starts/react/package-lock.json
starts/react/package.json
starts/react/public/index.html
starts/react/src/App.css
starts/react/src/App.js
starts/react/src/index.css
starts/react/src/index.js