Metadata-Version: 1.1
Name: django-genius
Version: 1.0.0
Summary: A package to create a folder via command line
Home-page: UNKNOWN
Author: Santhosh Parthiban
Author-email: santhoshparthiban2002@gmail.com
License: UNKNOWN
Platform: UNKNOWN
Classifier: Programming Language :: Python :: 3
Classifier: License :: OSI Approved :: MIT License
Classifier: Operating System :: OS Independent
